treehole/__init__.py
treehole/client.py
treehole/models.py
treehole/utils.py
TreeHole-2.0.0.dist-info/LICENSE.txt
TreeHole-2.0.0.dist-info/METADATA
TreeHole-2.0.0.dist-info/WHEEL
TreeHole-2.0.0.dist-info/top_level.txt
TreeHole-2.0.0.dist-info/RECORD
