Metadata-Version: 2.1
Name: TreeHole
Version: 2.0.0
Summary: A Python interface to PKU Hole!
Author-email: TeddyHuang-00 <huang_nan_2019@pku.edu.cn>
Project-URL: Homepage, https://github.com/TeddyHuang-00/pyTreeHole
Project-URL: Bug Tracker, https://github.com/TeddyHuang-00/pyTreeHole/issues
Project-URL: Documentation, https://teddyhuang-00.github.io/pyTreeHole/
Project-URL: Changelog, https://github.com/TeddyHuang-00/pyTreeHole/blob/main/CHANGELOG.md
Keywords: pku,hole,treehole,aiohttp,requests
Classifier: Programming Language :: Python :: 3
Classifier: License :: OSI Approved :: MIT License
Classifier: Operating System :: OS Independent
Requires-Python: >=3.6
License-File: LICENSE.txt
Requires-Dist: requests
Requires-Dist: aiohttp
Requires-Dist: aiofiles
Provides-Extra: test
Requires-Dist: setuptools ; extra == 'test'
Requires-Dist: rich ; extra == 'test'
Requires-Dist: pytest ; extra == 'test'
Requires-Dist: pytest-asyncio ; extra == 'test'
Requires-Dist: pytest-json-report ; extra == 'test'
Requires-Dist: vermin ; extra == 'test'
Requires-Dist: pdoc ; extra == 'test'
